wavecom/__init__.py
wavecom/__main__.py
wavecom/_main.py
wavecom-0.0.0.dist-info/METADATA
wavecom-0.0.0.dist-info/WHEEL
wavecom-0.0.0.dist-info/entry_points.txt
wavecom-0.0.0.dist-info/RECORD
