Metadata-Version: 2.1
Name: wavecom
Version: 0.0.0
Summary: Wavecom python common tooling
Author-email: Informatica <informatica@wavesys.pt>
Requires-Python: >=3.11
Provides-Extra: dev
Provides-Extra: docs
